{
    "ObservationFormName": "Death Note",
    "ObservationFormDetails": [
        {
            "type": "Date",
            "label": "Date of death",
            "value": -4
        },
        {
            "type": "Button",
            "label": "Probable cause of death",
            "value": "Postpartum Maternal Death"
        },
        {
            "type": "Button",
            "label": "Brought in dead",
            "short_name": "Dead on Arrival at Hospital",
            "value": "No"
        }
    ]
}